{
  "component": "ArcLabel",
  "examples": [],
  "usage": [
    {
      "example": "basic",
      "component": "Chord",
      "path": "/docs/components/Chord/basic",
      "lineNumber": 46,
      "line": "<ArcLabel"
    },
    {
      "example": "directed",
      "component": "Chord",
      "path": "/docs/components/Chord/directed",
      "lineNumber": 47,
      "line": "<ArcLabel"
    },
    {
      "example": "gradient",
      "component": "Chord",
      "path": "/docs/components/Chord/gradient",
      "lineNumber": 116,
      "line": "<ArcLabel"
    },
    {
      "example": "hover",
      "component": "Chord",
      "path": "/docs/components/Chord/hover",
      "lineNumber": 127,
      "line": "<ArcLabel"
    },
    {
      "example": "sunburst",
      "component": "Partition",
      "path": "/docs/components/Partition/sunburst",
      "lineNumber": 128,
      "line": "<ArcLabel"
    }
  ],
  "updatedAt": "2026-04-12T22:48:24.624Z"
}